megabot/__init__.py
megabot/command.py
megabot/dispatcher.py
megabot/sender.py
megabot/models/__init__.py
megabot/models/base.py
megabot/models/callback.py
megabot/models/chats.py
megabot/models/command.py
megabot/models/emodj.py
megabot/models/file.py
megabot/models/forum.py
megabot/models/game.py
megabot/models/keyboards.py
megabot/models/media.py
megabot/models/message.py
megabot/models/payment.py
megabot/models/photo.py
megabot/models/poll.py
megabot/models/sticker.py
megabot/models/users.py
megabot/models/video.py
megabot/models/web_app.py
megabot/utils/__init__.py
megabot/utils/callback_data.py
megabot-0.0.6.dist-info/LICENSE
megabot-0.0.6.dist-info/METADATA
megabot-0.0.6.dist-info/WHEEL
megabot-0.0.6.dist-info/top_level.txt
megabot-0.0.6.dist-info/RECORD
