Metadata-Version: 2.1
Name: megabot
Version: 0.0.6
Summary: Python telegram API adapter for FastAPI and asyncio
Home-page: https://github.com/imoknot/megabot
Author: Aleksandr Koksharov
Author-email: koksharov@yandex.ru
License: MIT
Project-URL: Bug Tracker, https://github.com/imoknot/megabot/issues
Project-URL: Changelog, https://github.com/imoknot/megabot/blob/master/CHANGELOG.md
Classifier: Development Status :: 2 - Pre-Alpha
Classifier: Programming Language :: Python :: 3.10
Classifier: Programming Language :: Python :: 3.11
Classifier: Programming Language :: Python :: 3.12
Classifier: License :: OSI Approved :: MIT License
Classifier: Operating System :: OS Independent
Classifier: Topic :: Software Development :: Libraries :: Python Modules
Requires-Python: >=3.10
License-File: LICENSE
Requires-Dist: requests
Requires-Dist: pydantic
